anime_list_apis/__init__.py
anime_list_apis/api/AnilistApi.py
anime_list_apis/api/ApiInterface.py
anime_list_apis/api/KitsuApi.py
anime_list_apis/api/MyanimelistApi.py
anime_list_apis/api/__init__.py
anime_list_apis/cache/Cache.py
anime_list_apis/cache/__init__.py
anime_list_apis/models/CacheAble.py
anime_list_apis/models/MediaData.py
anime_list_apis/models/MediaListEntry.py
anime_list_apis/models/MediaUserData.py
anime_list_apis/models/Serializable.py
anime_list_apis/models/__init__.py
anime_list_apis/models/attributes/ConsumingStatus.py
anime_list_apis/models/attributes/Date.py
anime_list_apis/models/attributes/Id.py
anime_list_apis/models/attributes/MediaType.py
anime_list_apis/models/attributes/Relation.py
anime_list_apis/models/attributes/ReleasingStatus.py
anime_list_apis/models/attributes/Score.py
anime_list_apis/models/attributes/Title.py
anime_list_apis/models/attributes/__init__.py
anime_list_apis/test/__init__.py
anime_list_apis/test/api/TestAnilistApi.py
anime_list_apis/test/api/__init__.py
anime_list_apis/test/cache/TestCache.py
anime_list_apis/test/cache/__init__.py
anime_list_apis/test/models/TestCacheAble.py
anime_list_apis/test/models/TestMediaData.py
anime_list_apis/test/models/TestMediaListEntry.py
anime_list_apis/test/models/TestMediaUserData.py
anime_list_apis/test/models/__init__.py
anime_list_apis/test/models/attributes/TestDate.py
anime_list_apis/test/models/attributes/TestId.py
anime_list_apis/test/models/attributes/TestRelation.py
anime_list_apis/test/models/attributes/TestScore.py
anime_list_apis/test/models/attributes/TestTitle.py
anime_list_apis/test/models/attributes/__init__.py
anime_list_apis-0.3.0.dist-info/METADATA
anime_list_apis-0.3.0.dist-info/RECORD
anime_list_apis-0.3.0.dist-info/WHEEL
anime_list_apis-0.3.0.dist-info/top_level.txt
