Metadata-Version: 2.1
Name: anime-list-apis
Version: 0.3.0
Summary: Collection of API wrappers for anime list sites
Home-page: https://gitlab.namibsun.net/namibsun/python/anime-list-apis
Author: Hermann Krumrey
Author-email: hermann@krumreyh.com
License: GNU GPL3
Platform: UNKNOWN
Classifier: License :: OSI Approved :: GNU General Public License v3 (GPLv3)
Requires-Dist: typing
Requires-Dist: requests
